{"skeleton":{"hash":"LbWyB49uHAp37MZfdtwltPjteE0","spine":"3.8.99","x":-47.03,"y":-64.08,"width":154,"height":167.67,"images":"","audio":""},"bones":[{"name":"root","x":-8.89,"y":3.52},{"name":"mouse","parent":"root"},{"name":"뼈","parent":"mouse","x":31.59,"y":29.65},{"name":"뼈2","parent":"뼈","length":14,"x":-15.27,"y":0.16},{"name":"뼈3","parent":"뼈","length":12,"rotation":-170,"x":11.99,"y":2.5},{"name":"lefteye","parent":"root"},{"name":"righteye","parent":"root"},{"name":"face","parent":"root"},{"name":"body","parent":"root"},{"name":"hand","parent":"root"}],"slots":[{"name":"body","bone":"body","attachment":"body"},{"name":"face","bone":"face","attachment":"face"},{"name":"lefteye","bone":"lefteye","attachment":"lefteye"},{"name":"righteye","bone":"righteye","attachment":"righteye"},{"name":"mouse","bone":"mouse","attachment":"mouse"},{"name":"hand","bone":"hand","attachment":"hand"}],"skins":[{"name":"default","attachments":{"body":{"body":{"x":27.11,"y":14.65,"width":130,"height":60}},"face":{"face":{"x":27.59,"y":58.57,"width":100,"height":83}},"hand":{"hand":{"x":38.86,"y":-20.6,"width":154,"height":94}},"lefteye":{"lefteye":{"x":6.63,"y":57.57,"width":23,"height":12}},"mouse":{"mouse":{"x":29.97,"y":28.41,"width":32,"height":11}},"righteye":{"righteye":{"x":46.64,"y":59.52,"width":22,"height":11}}}}],"animations":{"hit":{"bones":{"mouse":{"rotate":[{},{"time":2,"angle":2},{"time":4}],"translate":[{},{"time":2,"x":4.12,"y":9.1},{"time":4}],"scale":[{},{"time":2,"x":0.7,"y":0.7},{"time":4}]},"lefteye":{"rotate":[{},{"time":2,"angle":4},{"time":4}],"translate":[{},{"time":2,"x":-2.74,"y":22.36},{"time":4,"y":-0.6}],"scale":[{},{"time":2,"y":0.6},{"time":4}]},"righteye":{"rotate":[{"angle":0.4},{"time":2,"angle":1.2},{"time":4}],"translate":[{},{"time":2,"x":-2.63,"y":20.94},{"time":4}],"scale":[{},{"time":2,"y":0.7},{"time":4}]},"face":{"rotate":[{},{"time":2,"angle":3.44},{"time":4}],"translate":[{},{"time":2,"x":-0.49,"y":1.17},{"time":4}]},"body":{"rotate":[{},{"time":2,"angle":3.88},{"time":4}],"translate":[{},{"time":2,"x":-0.58,"y":0.69},{"time":4}]},"hand":{"rotate":[{},{"time":2,"angle":2.16},{"time":4}],"translate":[{},{"time":2,"x":0.77,"y":-1.61},{"time":4,"x":1,"y":1}],"scale":[{},{"time":2,"y":1.05},{"time":4}]}}},"normal":{"bones":{"mouse":{"rotate":[{},{"time":2,"angle":2},{"time":4}],"translate":[{},{"time":2,"x":4.12,"y":9.1},{"time":4}],"scale":[{},{"time":2,"x":0.7,"y":0.7},{"time":4}]},"lefteye":{"rotate":[{},{"time":2,"angle":4},{"time":4}],"translate":[{},{"time":2,"x":-1.3,"y":1.84},{"time":4}]},"righteye":{"rotate":[{"angle":0.4},{"time":4}],"translate":[{},{"time":2,"x":-2.57,"y":3.5},{"time":4}]},"face":{"rotate":[{},{"time":2,"angle":3.44},{"time":4}],"translate":[{},{"time":2,"x":-0.49,"y":1.17},{"time":4}]},"body":{"rotate":[{},{"time":2,"angle":3.02},{"time":4}],"translate":[{},{"time":2,"x":-0.58,"y":0.69},{"time":4}]},"hand":{"rotate":[{},{"time":2,"angle":5},{"time":4}],"translate":[{},{"time":2,"x":1.39,"y":2.24},{"time":4,"x":1,"y":1}],"scale":[{},{"time":2,"x":1.02,"y":1.02},{"time":4}]}}}}}